JavascriptMimiHuayuan/README.md
JavascriptMimiHuayuan/__init__.py
JavascriptMimiHuayuan/__main__.py
JavascriptMimiHuayuan/file.epub
JavascriptMimiHuayuan/index.html
JavascriptMimiHuayuan/css/__init__.py
JavascriptMimiHuayuan/css/annotations.css
JavascriptMimiHuayuan/css/main.css
JavascriptMimiHuayuan/css/normalize.css
JavascriptMimiHuayuan/css/popup.css
JavascriptMimiHuayuan/font/__init__.py
JavascriptMimiHuayuan/font/fontello.eot
JavascriptMimiHuayuan/font/fontello.svg
JavascriptMimiHuayuan/font/fontello.ttf
JavascriptMimiHuayuan/font/fontello.woff
JavascriptMimiHuayuan/img/__init__.py
JavascriptMimiHuayuan/img/annotator-glyph-sprite.png
JavascriptMimiHuayuan/img/annotator-icon-sprite.png
JavascriptMimiHuayuan/img/apple-touch-icon.png
JavascriptMimiHuayuan/img/cancelfullscreen.png
JavascriptMimiHuayuan/img/close.png
JavascriptMimiHuayuan/img/fullscreen.png
JavascriptMimiHuayuan/img/loader.gif
JavascriptMimiHuayuan/img/menu-icon.png
JavascriptMimiHuayuan/img/save.png
JavascriptMimiHuayuan/img/saved.png
JavascriptMimiHuayuan/img/settings-s.png
JavascriptMimiHuayuan/img/settings.png
JavascriptMimiHuayuan/img/star.png
JavascriptMimiHuayuan/js/__init__.py
JavascriptMimiHuayuan/js/epub.js
JavascriptMimiHuayuan/js/epub.min.js
JavascriptMimiHuayuan/js/epub.min.map
JavascriptMimiHuayuan/js/hooks.min.js
JavascriptMimiHuayuan/js/hooks.min.map
JavascriptMimiHuayuan/js/reader.js
JavascriptMimiHuayuan/js/reader.js.map
JavascriptMimiHuayuan/js/reader.min.js
JavascriptMimiHuayuan/js/reader.min.map
JavascriptMimiHuayuan/js/hooks/__init__.py
JavascriptMimiHuayuan/js/hooks/extensions/__init__.py
JavascriptMimiHuayuan/js/hooks/extensions/highlight.js
JavascriptMimiHuayuan/js/libs/__init__.py
JavascriptMimiHuayuan/js/libs/jquery.min.js
JavascriptMimiHuayuan/js/libs/localforage.min.js
JavascriptMimiHuayuan/js/libs/screenfull.js
JavascriptMimiHuayuan/js/libs/screenfull.min.js
JavascriptMimiHuayuan/js/libs/zip.min.js
JavascriptMimiHuayuan/js/plugins/__init__.py
javascript_mimi_huayuan-2024.3.1.0.dist-info/METADATA
javascript_mimi_huayuan-2024.3.1.0.dist-info/WHEEL
javascript_mimi_huayuan-2024.3.1.0.dist-info/entry_points.txt
javascript_mimi_huayuan-2024.3.1.0.dist-info/top_level.txt
javascript_mimi_huayuan-2024.3.1.0.dist-info/RECORD
